akeneo/__init__.py
akeneo/api.py
akeneo/test.py
akeneo/version.py
akeneo-0.0.1.dist-info/DESCRIPTION.rst
akeneo-0.0.1.dist-info/METADATA
akeneo-0.0.1.dist-info/RECORD
akeneo-0.0.1.dist-info/WHEEL
akeneo-0.0.1.dist-info/metadata.json
akeneo-0.0.1.dist-info/top_level.txt
