Metadata-Version: 2.0
Name: akeneo
Version: 0.0.1
Summary: A Python wrapper for the Akeneo REST API
Home-page: https://github.com/AuguriaTeam/python-akeneo
Author: Auguria
Author-email: UNKNOWN
License: LICENSE
Platform: any
Classifier: Development Status :: 5 - Production/Stable
Classifier: Operating System :: OS Independent
Classifier: Intended Audience :: Developers
Classifier: Natural Language :: English
Classifier: License :: OSI Approved :: GNU Lesser General Public License v3 (LGPLv3)
Classifier: Programming Language :: Python
Classifier: Programming Language :: Python :: 2.7
Classifier: Programming Language :: Python :: 3.4
Classifier: Programming Language :: Python :: 3.5
Classifier: Topic :: Software Development :: Libraries :: Python Modules
Requires-Dist: requests-toolbelt
Requires-Dist: requests
Requires-Dist: urllib3
